config_logs/__init__.py
config_logs/config_logs.py
rabbitmq_async_client/__init__.py
rabbitmq_async_client/rabbitmq_client.py
tests/__init__.py
tests/conf_rabbit.py
tests/cosumer.py
tests/init_queues.py
tests/publisher.py
tests/pull.py
tests/push.py
async_rabbitmq-0.1.0.dist-info/LICENSE
async_rabbitmq-0.1.0.dist-info/METADATA
async_rabbitmq-0.1.0.dist-info/WHEEL
async_rabbitmq-0.1.0.dist-info/top_level.txt
async_rabbitmq-0.1.0.dist-info/RECORD
